gobby/__init__.py
gobby/app_context.py
gobby/paths.py
gobby/py.typed
gobby/runner.py
gobby/adapters/__init__.py
gobby/adapters/base.py
gobby/adapters/claude_code.py
gobby/adapters/gemini.py
gobby/adapters/codex_impl/__init__.py
gobby/adapters/codex_impl/adapter.py
gobby/adapters/codex_impl/client.py
gobby/adapters/codex_impl/protocol.py
gobby/adapters/codex_impl/types.py
gobby/agents/__init__.py
gobby/agents/codex_session.py
gobby/agents/constants.py
gobby/agents/context.py
gobby/agents/definitions.py
gobby/agents/gemini_session.py
gobby/agents/isolation.py
gobby/agents/registry.py
gobby/agents/runner.py
gobby/agents/sandbox.py
gobby/agents/session.py
gobby/agents/spawn.py
gobby/agents/spawn_executor.py
gobby/agents/tty_config.py
gobby/agents/spawners/__init__.py
gobby/agents/spawners/base.py
gobby/agents/spawners/command_builder.py
gobby/agents/spawners/cross_platform.py
gobby/agents/spawners/embedded.py
gobby/agents/spawners/headless.py
gobby/agents/spawners/linux.py
gobby/agents/spawners/macos.py
gobby/agents/spawners/prompt_manager.py
gobby/agents/spawners/windows.py
gobby/autonomous/__init__.py
gobby/autonomous/progress_tracker.py
gobby/autonomous/stop_registry.py
gobby/autonomous/stuck_detector.py
gobby/cli/__init__.py
gobby/cli/__main__.py
gobby/cli/agents.py
gobby/cli/artifacts.py
gobby/cli/clones.py
gobby/cli/conductor.py
gobby/cli/daemon.py
gobby/cli/extensions.py
gobby/cli/github.py
gobby/cli/init.py
gobby/cli/install.py
gobby/cli/linear.py
gobby/cli/mcp.py
gobby/cli/mcp_proxy.py
gobby/cli/memory.py
gobby/cli/merge.py
gobby/cli/projects.py
gobby/cli/sessions.py
gobby/cli/skills.py
gobby/cli/utils.py
gobby/cli/workflows.py
gobby/cli/worktrees.py
gobby/cli/installers/__init__.py
gobby/cli/installers/antigravity.py
gobby/cli/installers/claude.py
gobby/cli/installers/codex.py
gobby/cli/installers/gemini.py
gobby/cli/installers/git_hooks.py
gobby/cli/installers/shared.py
gobby/cli/tasks/__init__.py
gobby/cli/tasks/_utils.py
gobby/cli/tasks/ai.py
gobby-0.2.9.dist-info/licenses/LICENSE.md
gobby-0.2.9.dist-info/METADATA
gobby-0.2.9.dist-info/WHEEL
gobby-0.2.9.dist-info/entry_points.txt
gobby-0.2.9.dist-info/top_level.txt
gobby-0.2.9.dist-info/RECORD
