Metadata-Version: 2.4
Name: gobby
Version: 0.2.9
Summary: A local-first daemon to unify your AI coding tools. Session tracking and handoffs across Claude Code, Gemini CLI, and Codex. An MCP proxy that discovers tools without flooding context. Task management with dependencies, validation, and TDD expansion. Agent spawning and worktree orchestration. Persistent memory, extensible workflows, and hooks.
Author-email: Josh Wilhelmi <josh@gobby.ai>
License-Expression: MIT
Project-URL: Homepage, https://github.com/GobbyAI/gobby
Project-URL: Repository, https://github.com/GobbyAI/gobby
Project-URL: Documentation, https://github.com/GobbyAI/gobby#readme
Project-URL: Issues, https://github.com/GobbyAI/gobby/issues
Keywords: cli,mcp,claude,gemini,codex,daemon,session-management
Classifier: Development Status :: 3 - Alpha
Classifier: Environment :: Console
Classifier: Intended Audience :: Developers
Classifier: Programming Language :: Python :: 3.13
Classifier: Programming Language :: Python :: 3.14
Classifier: Topic :: Software Development :: Libraries :: Python Modules
Requires-Python: >=3.13
License-File: LICENSE.md
Requires-Dist: anthropic>=0.75.0
Requires-Dist: click>=8.1.0
Requires-Dist: fastapi>=0.115.0
Requires-Dist: fastmcp>=2.14.0
Requires-Dist: httpx>=0.27.0
Requires-Dist: litellm>=1.0.0
Requires-Dist: psutil>=6.1.0
Requires-Dist: py-machineid>=0.6.0
Requires-Dist: pydantic>=2.9.0
Requires-Dist: uvicorn[standard]>=0.30.0
Requires-Dist: websockets>=15.0
Requires-Dist: pyyaml>=6.0.3
Requires-Dist: jinja2>=3.1.0
Requires-Dist: claude-agent-sdk>=0.1.18
Requires-Dist: wcwidth>=0.2.14
Requires-Dist: tomli-w>=1.0.0
Requires-Dist: msgspec>=0.20.0
Requires-Dist: gitingest>=0.3.1
Requires-Dist: scikit-learn>=1.0.0
Requires-Dist: textual>=7.3.0
Requires-Dist: memu-py>=1.0.0
Requires-Dist: python-multipart>=0.0.22
Provides-Extra: mem0
Requires-Dist: mem0ai; extra == "mem0"
Dynamic: license-file
